meta_screening/__init__.py
meta_screening/admin_site.py
meta_screening/apps.py
meta_screening/calculators.py
meta_screening/choices.py
meta_screening/constants.py
meta_screening/eligibility.py
meta_screening/mommy_recipes.py
meta_screening/offline_models.py
meta_screening/reportables.py
meta_screening/signals.py
meta_screening/urls.py
meta_screening/admin/__init__.py
meta_screening/admin/fieldsets.py
meta_screening/admin/icp_referral_admin.py
meta_screening/admin/screening_part_one_admin.py
meta_screening/admin/screening_part_three_admin.py
meta_screening/admin/screening_part_two_admin.py
meta_screening/admin/subject_refusal_admin.py
meta_screening/admin/subject_screening_admin.py
meta_screening/form_validators/__init__.py
meta_screening/form_validators/screening_part_one.py
meta_screening/form_validators/screening_part_three.py
meta_screening/form_validators/screening_part_two.py
meta_screening/form_validators/subject_refusal.py
meta_screening/form_validators/subject_screening.py
meta_screening/forms/__init__.py
meta_screening/forms/field_lists.py
meta_screening/forms/screening_part_one_form.py
meta_screening/forms/screening_part_three_form.py
meta_screening/forms/screening_part_two_form.py
meta_screening/forms/subject_refusal_form.py
meta_screening/forms/subject_screening_form.py
meta_screening/migrations/0001_initial.py
meta_screening/migrations/0002_auto_20191020_0612.py
meta_screening/migrations/0003_auto_20191020_0627.py
meta_screening/migrations/0004_auto_20191020_0738.py
meta_screening/migrations/0005_auto_20191021_0353.py
meta_screening/migrations/0006_auto_20191022_0134.py
meta_screening/migrations/0007_auto_20191024_1000.py
meta_screening/migrations/0008_auto_20191031_0745.py
meta_screening/migrations/0009_auto_20191105_0122.py
meta_screening/migrations/0010_auto_20191106_0828.py
meta_screening/migrations/0011_auto_20191107_0342.py
meta_screening/migrations/0012_auto_20191107_0427.py
meta_screening/migrations/0013_auto_20191107_0442.py
meta_screening-0.1.36.dist-info/AUTHORS
meta_screening-0.1.36.dist-info/LICENSE
meta_screening-0.1.36.dist-info/METADATA
meta_screening-0.1.36.dist-info/WHEEL
meta_screening-0.1.36.dist-info/top_level.txt
meta_screening-0.1.36.dist-info/RECORD
